MANIFEST.in
README
setup.py
share/defaults
share/thinkpad.png
share/trayicon_off.png
share/trayicon_on.png
src/thinkwhack/__init__.py
src/thinkwhack/actions.py
src/thinkwhack/config.py
src/thinkwhack/tests.py
src/thinkwhack/thinkwhack.py
thinkwhack.egg-info/PKG-INFO
thinkwhack.egg-info/SOURCES.txt
thinkwhack.egg-info/dependency_links.txt
thinkwhack.egg-info/entry_points.txt
thinkwhack.egg-info/top_level.txt