Metadata-Version: 1.0
Name: thinkwhack
Version: 0.2
Summary: Thinkwhack allows you to use your thinkpad's hdaps sensors to trigger actions.
Home-page: http://the-gay-bar.com/thinkwhack/
Author: Juergen Geuter
Author-email: tante@the-gay-bar.com
License: GNU GPL-3
Download-URL: http://the-gay-bar.com/thinkwhack/dist/
Keywords: hdaps thinkpad
Platform: UNKNOWN
